{
  "collectionName": "components_blocks_paragraph_with_images",
  "info": {
    "displayName": "Paragraph With Image"
  },
  "options": {},
  "attributes": {
    "image": {
      "type": "media",
      "multiple": false,
      "allowedTypes": [
        "images"
      ]
    },
    "reversed": {
      "type": "boolean",
      "default": false
    },
    "imageLandscape": {
      "type": "boolean",
      "default": true
    },
    "content": {
      "type": "customField",
      "customField": "plugin::ckeditor5.CKEditor",
      "options": {
        "preset": "defaultHtml"
      }
    }
  }
}
